MANIFEST.in
MIT_LICENSE
README.md
requirements.txt
setup.cfg
setup.py
metrics.gitinfo.egg-info/PKG-INFO
metrics.gitinfo.egg-info/SOURCES.txt
metrics.gitinfo.egg-info/dependency_links.txt
metrics.gitinfo.egg-info/entry_points.txt
metrics.gitinfo.egg-info/requires.txt
metrics.gitinfo.egg-info/top_level.txt
metrics_gitinfo/__init__.py
metrics_gitinfo/file_info.py
metrics_gitinfo/git_diff_muncher.py
metrics_gitinfo/gitinfo.py