Metadata-Version: 1.1
Name: metrics.gitinfo
Version: 0.0.5
Summary: plugin for the metrics package (extracts changed lines, author, ...)
Home-page: https://github.com/markfink/metrics.gitinfo/
Author: Mark Fink
Author-email: mark@mark-fink.de
License: MIT
Platform: UNKNOWN
Classifier: Natural Language :: English
Classifier: Intended Audience :: Developers
Classifier: Environment :: Console
Classifier: License :: OSI Approved :: MIT License
Classifier: Programming Language :: Python :: 2.7
Classifier: Programming Language :: Python :: 3.6
